pvfr/passeport_credential/__init__.py
pvfr_passeport_credential-1.0.2.dist-info/METADATA
pvfr_passeport_credential-1.0.2.dist-info/RECORD
pvfr_passeport_credential-1.0.2.dist-info/WHEEL
pvfr_passeport_credential-1.0.2.dist-info/top_level.txt
